{

    "parts" : [
        {
          "id": "Sheet ingots",
          "label": "Sheet ingots",
          "totalValue": "$68 M",
          "value": 57,
          "color": "#60c49f"
        },
        {
          "id": "Extrusion ingots",
          "label": "Extrusion ingots",
          "totalValue": "$102 M",
          "value": 43,
          "color": "#f2bb23"
        },
        {
          "id": "Wire rod",
          "label": "Wire rod",
          "totalValue": "$78 M",
          "value": 22,
          "color": "#eb7f3e"
        },
        {
          "id": "Primary foundry alloys",
          "label": "Primary foundry alloys",
          "totalValue": "$109 M",
          "value": 160,
          "color": "#4788fe"
        }
    ]
}